datalad/__init__.py
datalad/__main__.py
datalad/_version.py
datalad/api.py
datalad/cmd.py
datalad/config.py
datalad/conftest.py
datalad/consts.py
datalad/coreapi.py
datalad/dochelpers.py
datalad/log.py
datalad/typing.py
datalad/utils.py
datalad/version.py
datalad/cli/__init__.py
datalad/cli/common_args.py
datalad/cli/exec.py
datalad/cli/helpers.py
datalad/cli/interface.py
datalad/cli/main.py
datalad/cli/parser.py
datalad/cli/renderer.py
datalad/cli/utils.py
datalad/cli/tests/__init__.py
datalad/cli/tests/test_exec.py
datalad/cli/tests/test_formatters.py
datalad/cli/tests/test_helpers.py
datalad/cli/tests/test_interface.py
datalad/cli/tests/test_main.py
datalad/cli/tests/test_parser.py
datalad/cli/tests/test_renderer.py
datalad/cli/tests/test_utils.py
datalad/cmdline/__init__.py
datalad/cmdline/helpers.py
datalad/cmdline/main.py
datalad/core/__init__.py
datalad/core/distributed/__init__.py
datalad/core/distributed/clone.py
datalad/core/distributed/clone_ephemeral.py
datalad/core/distributed/clone_ria.py
datalad/core/distributed/clone_utils.py
datalad/core/distributed/push.py
datalad/core/distributed/tests/__init__.py
datalad/core/distributed/tests/test_clone.py
datalad/core/distributed/tests/test_push.py
datalad/core/local/__init__.py
datalad/core/local/create.py
datalad/core/local/diff.py
datalad/core/local/repo.py
datalad/core/local/resulthooks.py
datalad/core/local/run.py
datalad/core/local/save.py
datalad/core/local/status.py
datalad/core/local/tests/__init__.py
datalad/core/local/tests/test_create.py
datalad/core/local/tests/test_diff.py
datalad/core/local/tests/test_resulthooks.py
datalad/core/local/tests/test_results.py
datalad/core/local/tests/test_run.py
datalad/core/local/tests/test_save.py
datalad/core/local/tests/test_status.py
datalad/customremotes/__init__.py
datalad/customremotes/archives.py
datalad/customremotes/base.py
datalad/customremotes/datalad.py
datalad/customremotes/main.py
datalad/customremotes/ria_remote.py
datalad-1.3.1.dist-info/licenses/COPYING
datalad-1.3.1.dist-info/METADATA
datalad-1.3.1.dist-info/WHEEL
datalad-1.3.1.dist-info/entry_points.txt
datalad-1.3.1.dist-info/top_level.txt
datalad-1.3.1.dist-info/RECORD
