Metadata-Version: 2.4
Name: datalad
Version: 1.3.1
Summary: Distributed system for joint management of code, data, and their relationship
Author-email: The DataLad Team and Contributors <team@datalad.org>
License-Expression: MIT
Project-URL: Homepage, https://www.datalad.org
Project-URL: Developer docs, https://docs.datalad.org/en/stable
Project-URL: Documentation, https://handbook.datalad.org
Project-URL: Repository, https://github.com/datalad/datalad
Project-URL: Issues, https://github.com/datalad/datalad/issues
Project-URL: RRID, https://identifiers.org/RRID:SCR_003931
Classifier: Development Status :: 5 - Production/Stable
Classifier: Environment :: Console
Classifier: Intended Audience :: Developers
Classifier: Intended Audience :: Education
Classifier: Intended Audience :: End Users/Desktop
Classifier: Intended Audience :: Science/Research
Classifier: Natural Language :: English
Classifier: Operating System :: POSIX
Classifier: Programming Language :: Python :: 3 :: Only
Classifier: Programming Language :: Unix Shell
Classifier: Topic :: Communications :: File Sharing
Classifier: Topic :: Education
Classifier: Topic :: Internet
Classifier: Topic :: Other/Nonlisted Topic
Classifier: Topic :: Scientific/Engineering
Classifier: Topic :: Software Development :: Libraries :: Python Modules
Classifier: Topic :: Software Development :: Version Control :: Git
Classifier: Topic :: Utilities
Requires-Python: >=3.10
License-File: COPYING
Requires-Dist: platformdirs
Requires-Dist: chardet>=3.0.4
Requires-Dist: colorama; platform_system == "Windows"
Requires-Dist: distro
Requires-Dist: iso8601
Requires-Dist: humanize
Requires-Dist: fasteners>=0.14
Requires-Dist: packaging
Requires-Dist: patool>=1.7
Requires-Dist: tqdm>=4.32.0
Requires-Dist: typing_extensions>=4.0.0; python_version < "3.11"
Requires-Dist: annexremote
Requires-Dist: looseversion
Requires-Dist: boto3
Requires-Dist: keyring!=23.9.0,>=20.0
Requires-Dist: keyrings.alt
Requires-Dist: msgpack
Requires-Dist: requests>=1.2
Requires-Dist: python-gitlab
Provides-Extra: downloaders-extra
Requires-Dist: requests_ftp; extra == "downloaders-extra"
Provides-Extra: misc
Requires-Dist: argcomplete>=1.12.3; extra == "misc"
Requires-Dist: pyperclip; extra == "misc"
Requires-Dist: python-dateutil; extra == "misc"
Provides-Extra: tests
Requires-Dist: BeautifulSoup4; extra == "tests"
Requires-Dist: httpretty>=0.9.4; extra == "tests"
Requires-Dist: mypy; extra == "tests"
Requires-Dist: pytest>=7.0; extra == "tests"
Requires-Dist: pytest-cov; extra == "tests"
Requires-Dist: pytest-retry; extra == "tests"
Requires-Dist: pytest-fail-slow~=0.2; extra == "tests"
Requires-Dist: types-python-dateutil; extra == "tests"
Requires-Dist: types-requests; extra == "tests"
Requires-Dist: vcrpy; extra == "tests"
Provides-Extra: duecredit
Requires-Dist: duecredit; extra == "duecredit"
Provides-Extra: full
Requires-Dist: datalad[downloaders-extra,duecredit,misc,tests]; extra == "full"
Provides-Extra: devel-docs
Requires-Dist: pypandoc; extra == "devel-docs"
Requires-Dist: sphinx>=4.3.0; extra == "devel-docs"
Requires-Dist: sphinx-autodoc-typehints; extra == "devel-docs"
Requires-Dist: sphinx-rtd-theme>=0.5.1; extra == "devel-docs"
Provides-Extra: devel-utils
Requires-Dist: asv; extra == "devel-utils"
Requires-Dist: coverage!=7.13.1,!=7.6.5; extra == "devel-utils"
Requires-Dist: gprof2dot; extra == "devel-utils"
Requires-Dist: psutil; extra == "devel-utils"
Requires-Dist: pytest-xdist; extra == "devel-utils"
Requires-Dist: scriv; extra == "devel-utils"
Provides-Extra: devel
Requires-Dist: datalad[devel-docs,devel-utils,full]; extra == "devel"
Dynamic: license-file
